simstat/__init__.py
simstat/bootstrap.py
simstat/bootstrapTest.py
simstat/permTest.py
SimStat-0.1.dist-info/LICENSE
SimStat-0.1.dist-info/METADATA
SimStat-0.1.dist-info/WHEEL
SimStat-0.1.dist-info/top_level.txt
SimStat-0.1.dist-info/RECORD
